gradio_textlabeler/__init__.py
gradio_textlabeler/textlabeler.py
gradio_textlabeler/textlabeler.pyi
gradio_textlabeler/templates/component/index.js
gradio_textlabeler/templates/component/style.css
gradio_textlabeler/templates/example/index.js
gradio_textlabeler/templates/example/style.css
gradio_textlabeler-1.0.2.dist-info/METADATA
gradio_textlabeler-1.0.2.dist-info/WHEEL
gradio_textlabeler-1.0.2.dist-info/RECORD
